ethcoinerdater/__init__.py
ethcoinerdater/ethdata.py
ethcoinerdater-0.1.dist-info/licenses/LICENSE
ethcoinerdater-0.1.dist-info/METADATA
ethcoinerdater-0.1.dist-info/WHEEL
ethcoinerdater-0.1.dist-info/top_level.txt
ethcoinerdater-0.1.dist-info/RECORD
