Metadata-Version: 2.4
Name: ethcoinerdater
Version: 0.1
Summary: A simple tool to get ETH prices from CoinGecko
Home-page: https://github.com/yourusername/ethcoinerdater
Author: Your Name
Author-email: your.email@example.com
License: MIT
License-File: LICENSE
Requires-Dist: requests
Dynamic: author
Dynamic: author-email
Dynamic: home-page
Dynamic: license
Dynamic: license-file
Dynamic: requires-dist
Dynamic: summary
